{
  "last_updated": "2026-04-11T20:31:58.084361",
  "stations": {
    "KCATRUCK288": {
      "latest_screenshot": {
        "filename": "KCATRUCK288_20260411_203045.png",
        "path": "screenshots/KCATRUCK288_20260411_203045.png",
        "timestamp": "2026-04-11T20:30:45",
        "size": 134671,
        "type": "single"
      },
      "total_screenshots": 12,
      "all_screenshots": [
        {
          "filename": "KCATRUCK288_20260411_203045.png",
          "path": "screenshots/KCATRUCK288_20260411_203045.png",
          "timestamp": "2026-04-11T20:30:45",
          "size": 134671,
          "type": "single"
        },
        {
          "filename": "KCATRUCK288_20260411_163450.png",
          "path": "screenshots/KCATRUCK288_20260411_163450.png",
          "timestamp": "2026-04-11T16:34:50",
          "size": 135463,
          "type": "single"
        },
        {
          "filename": "KCATRUCK288_20260411_125349.png",
          "path": "screenshots/KCATRUCK288_20260411_125349.png",
          "timestamp": "2026-04-11T12:53:49",
          "size": 134473,
          "type": "single"
        },
        {
          "filename": "KCATRUCK288_20260411_084042.png",
          "path": "screenshots/KCATRUCK288_20260411_084042.png",
          "timestamp": "2026-04-11T08:40:42",
          "size": 135452,
          "type": "single"
        },
        {
          "filename": "KCATRUCK288_20260411_052425.png",
          "path": "screenshots/KCATRUCK288_20260411_052425.png",
          "timestamp": "2026-04-11T05:24:25",
          "size": 133213,
          "type": "single"
        },
        {
          "filename": "KCATRUCK288_20260411_020402.png",
          "path": "screenshots/KCATRUCK288_20260411_020402.png",
          "timestamp": "2026-04-11T02:04:02",
          "size": 137403,
          "type": "single"
        },
        {
          "filename": "KCATRUCK288_20260410_203402.png",
          "path": "screenshots/KCATRUCK288_20260410_203402.png",
          "timestamp": "2026-04-10T20:34:02",
          "size": 138430,
          "type": "single"
        },
        {
          "filename": "KCATRUCK288_20260410_165213.png",
          "path": "screenshots/KCATRUCK288_20260410_165213.png",
          "timestamp": "2026-04-10T16:52:13",
          "size": 139475,
          "type": "single"
        },
        {
          "filename": "KCATRUCK288_20260410_130519.png",
          "path": "screenshots/KCATRUCK288_20260410_130519.png",
          "timestamp": "2026-04-10T13:05:19",
          "size": 137748,
          "type": "single"
        },
        {
          "filename": "KCATRUCK288_20260410_090639.png",
          "path": "screenshots/KCATRUCK288_20260410_090639.png",
          "timestamp": "2026-04-10T09:06:39",
          "size": 140180,
          "type": "single"
        },
        {
          "filename": "KCATRUCK288_20260410_055631.png",
          "path": "screenshots/KCATRUCK288_20260410_055631.png",
          "timestamp": "2026-04-10T05:56:31",
          "size": 137475,
          "type": "single"
        },
        {
          "filename": "KCATRUCK288_20260410_022320.png",
          "path": "screenshots/KCATRUCK288_20260410_022320.png",
          "timestamp": "2026-04-10T02:23:20",
          "size": 137606,
          "type": "single"
        }
      ],
      "has_multiple_views": false,
      "is_full_page": false
    },
    "KCASQUAW15": {
      "latest_screenshot": {
        "filename": "KCASQUAW15_20260411_203015.png",
        "path": "screenshots/KCASQUAW15_20260411_203015.png",
        "timestamp": "2026-04-11T20:30:15",
        "size": 133855,
        "type": "single"
      },
      "total_screenshots": 12,
      "all_screenshots": [
        {
          "filename": "KCASQUAW15_20260411_203015.png",
          "path": "screenshots/KCASQUAW15_20260411_203015.png",
          "timestamp": "2026-04-11T20:30:15",
          "size": 133855,
          "type": "single"
        },
        {
          "filename": "KCASQUAW15_20260411_163421.png",
          "path": "screenshots/KCASQUAW15_20260411_163421.png",
          "timestamp": "2026-04-11T16:34:21",
          "size": 132337,
          "type": "single"
        },
        {
          "filename": "KCASQUAW15_20260411_125322.png",
          "path": "screenshots/KCASQUAW15_20260411_125322.png",
          "timestamp": "2026-04-11T12:53:22",
          "size": 132821,
          "type": "single"
        },
        {
          "filename": "KCASQUAW15_20260411_084016.png",
          "path": "screenshots/KCASQUAW15_20260411_084016.png",
          "timestamp": "2026-04-11T08:40:16",
          "size": 131139,
          "type": "single"
        },
        {
          "filename": "KCASQUAW15_20260411_052404.png",
          "path": "screenshots/KCASQUAW15_20260411_052404.png",
          "timestamp": "2026-04-11T05:24:04",
          "size": 135886,
          "type": "single"
        },
        {
          "filename": "KCASQUAW15_20260411_020331.png",
          "path": "screenshots/KCASQUAW15_20260411_020331.png",
          "timestamp": "2026-04-11T02:03:31",
          "size": 131350,
          "type": "single"
        },
        {
          "filename": "KCASQUAW15_20260410_203334.png",
          "path": "screenshots/KCASQUAW15_20260410_203334.png",
          "timestamp": "2026-04-10T20:33:34",
          "size": 134104,
          "type": "single"
        },
        {
          "filename": "KCASQUAW15_20260410_165148.png",
          "path": "screenshots/KCASQUAW15_20260410_165148.png",
          "timestamp": "2026-04-10T16:51:48",
          "size": 136191,
          "type": "single"
        },
        {
          "filename": "KCASQUAW15_20260410_130445.png",
          "path": "screenshots/KCASQUAW15_20260410_130445.png",
          "timestamp": "2026-04-10T13:04:45",
          "size": 132407,
          "type": "single"
        },
        {
          "filename": "KCASQUAW15_20260410_090607.png",
          "path": "screenshots/KCASQUAW15_20260410_090607.png",
          "timestamp": "2026-04-10T09:06:07",
          "size": 133130,
          "type": "single"
        },
        {
          "filename": "KCASQUAW15_20260410_055607.png",
          "path": "screenshots/KCASQUAW15_20260410_055607.png",
          "timestamp": "2026-04-10T05:56:07",
          "size": 132311,
          "type": "single"
        },
        {
          "filename": "KCASQUAW15_20260410_022256.png",
          "path": "screenshots/KCASQUAW15_20260410_022256.png",
          "timestamp": "2026-04-10T02:22:56",
          "size": 135606,
          "type": "single"
        }
      ],
      "has_multiple_views": false,
      "is_full_page": false
    },
    "KNVRENO347": {
      "latest_screenshot": {
        "filename": "KNVRENO347_20260411_203058.png",
        "path": "screenshots/KNVRENO347_20260411_203058.png",
        "timestamp": "2026-04-11T20:30:58",
        "size": 136148,
        "type": "single"
      },
      "total_screenshots": 12,
      "all_screenshots": [
        {
          "filename": "KNVRENO347_20260411_203058.png",
          "path": "screenshots/KNVRENO347_20260411_203058.png",
          "timestamp": "2026-04-11T20:30:58",
          "size": 136148,
          "type": "single"
        },
        {
          "filename": "KNVRENO347_20260411_163502.png",
          "path": "screenshots/KNVRENO347_20260411_163502.png",
          "timestamp": "2026-04-11T16:35:02",
          "size": 130803,
          "type": "single"
        },
        {
          "filename": "KNVRENO347_20260411_125400.png",
          "path": "screenshots/KNVRENO347_20260411_125400.png",
          "timestamp": "2026-04-11T12:54:00",
          "size": 133892,
          "type": "single"
        },
        {
          "filename": "KNVRENO347_20260411_084050.png",
          "path": "screenshots/KNVRENO347_20260411_084050.png",
          "timestamp": "2026-04-11T08:40:50",
          "size": 133218,
          "type": "single"
        },
        {
          "filename": "KNVRENO347_20260411_052434.png",
          "path": "screenshots/KNVRENO347_20260411_052434.png",
          "timestamp": "2026-04-11T05:24:34",
          "size": 138409,
          "type": "single"
        },
        {
          "filename": "KNVRENO347_20260411_020411.png",
          "path": "screenshots/KNVRENO347_20260411_020411.png",
          "timestamp": "2026-04-11T02:04:11",
          "size": 139580,
          "type": "single"
        },
        {
          "filename": "KNVRENO347_20260410_203413.png",
          "path": "screenshots/KNVRENO347_20260410_203413.png",
          "timestamp": "2026-04-10T20:34:13",
          "size": 137620,
          "type": "single"
        },
        {
          "filename": "KNVRENO347_20260410_165220.png",
          "path": "screenshots/KNVRENO347_20260410_165220.png",
          "timestamp": "2026-04-10T16:52:20",
          "size": 138875,
          "type": "single"
        },
        {
          "filename": "KNVRENO347_20260410_130530.png",
          "path": "screenshots/KNVRENO347_20260410_130530.png",
          "timestamp": "2026-04-10T13:05:30",
          "size": 134914,
          "type": "single"
        },
        {
          "filename": "KNVRENO347_20260410_090645.png",
          "path": "screenshots/KNVRENO347_20260410_090645.png",
          "timestamp": "2026-04-10T09:06:45",
          "size": 141625,
          "type": "single"
        },
        {
          "filename": "KNVRENO347_20260410_055638.png",
          "path": "screenshots/KNVRENO347_20260410_055638.png",
          "timestamp": "2026-04-10T05:56:38",
          "size": 112044,
          "type": "single"
        },
        {
          "filename": "KNVRENO347_20260410_022328.png",
          "path": "screenshots/KNVRENO347_20260410_022328.png",
          "timestamp": "2026-04-10T02:23:28",
          "size": 137765,
          "type": "single"
        }
      ],
      "has_multiple_views": false,
      "is_full_page": false
    },
    "NOAA_DESI_ALPINE": {
      "latest_screenshot": {
        "filename": "NOAA_DESI_ALPINE_20260411_203122.png",
        "path": "screenshots/NOAA_DESI_ALPINE_20260411_203122.png",
        "timestamp": "2026-04-11T20:31:22",
        "size": 408878,
        "type": "full_page"
      },
      "total_screenshots": 12,
      "all_screenshots": [
        {
          "filename": "NOAA_DESI_ALPINE_20260411_203122.png",
          "path": "screenshots/NOAA_DESI_ALPINE_20260411_203122.png",
          "timestamp": "2026-04-11T20:31:22",
          "size": 408878,
          "type": "full_page"
        },
        {
          "filename": "NOAA_DESI_ALPINE_20260411_163520.png",
          "path": "screenshots/NOAA_DESI_ALPINE_20260411_163520.png",
          "timestamp": "2026-04-11T16:35:20",
          "size": 409430,
          "type": "full_page"
        },
        {
          "filename": "NOAA_DESI_ALPINE_20260411_125423.png",
          "path": "screenshots/NOAA_DESI_ALPINE_20260411_125423.png",
          "timestamp": "2026-04-11T12:54:23",
          "size": 409203,
          "type": "full_page"
        },
        {
          "filename": "NOAA_DESI_ALPINE_20260411_084111.png",
          "path": "screenshots/NOAA_DESI_ALPINE_20260411_084111.png",
          "timestamp": "2026-04-11T08:41:11",
          "size": 411844,
          "type": "full_page"
        },
        {
          "filename": "NOAA_DESI_ALPINE_20260411_052454.png",
          "path": "screenshots/NOAA_DESI_ALPINE_20260411_052454.png",
          "timestamp": "2026-04-11T05:24:54",
          "size": 411844,
          "type": "full_page"
        },
        {
          "filename": "NOAA_DESI_ALPINE_20260411_020433.png",
          "path": "screenshots/NOAA_DESI_ALPINE_20260411_020433.png",
          "timestamp": "2026-04-11T02:04:33",
          "size": 413750,
          "type": "full_page"
        },
        {
          "filename": "NOAA_DESI_ALPINE_20260410_203436.png",
          "path": "screenshots/NOAA_DESI_ALPINE_20260410_203436.png",
          "timestamp": "2026-04-10T20:34:36",
          "size": 416632,
          "type": "full_page"
        },
        {
          "filename": "NOAA_DESI_ALPINE_20260410_165241.png",
          "path": "screenshots/NOAA_DESI_ALPINE_20260410_165241.png",
          "timestamp": "2026-04-10T16:52:41",
          "size": 17564,
          "type": "full_page"
        },
        {
          "filename": "NOAA_DESI_ALPINE_20260410_130604.png",
          "path": "screenshots/NOAA_DESI_ALPINE_20260410_130604.png",
          "timestamp": "2026-04-10T13:06:04",
          "size": 419094,
          "type": "full_page"
        },
        {
          "filename": "NOAA_DESI_ALPINE_20260410_090706.png",
          "path": "screenshots/NOAA_DESI_ALPINE_20260410_090706.png",
          "timestamp": "2026-04-10T09:07:06",
          "size": 354191,
          "type": "full_page"
        },
        {
          "filename": "NOAA_DESI_ALPINE_20260410_055700.png",
          "path": "screenshots/NOAA_DESI_ALPINE_20260410_055700.png",
          "timestamp": "2026-04-10T05:57:00",
          "size": 417820,
          "type": "full_page"
        },
        {
          "filename": "NOAA_DESI_ALPINE_20260410_022349.png",
          "path": "screenshots/NOAA_DESI_ALPINE_20260410_022349.png",
          "timestamp": "2026-04-10T02:23:49",
          "size": 417386,
          "type": "full_page"
        }
      ],
      "has_multiple_views": false,
      "is_full_page": true
    },
    "KCAOLYMP3": {
      "latest_screenshot": {
        "filename": "KCAOLYMP3_20260411_203035.png",
        "path": "screenshots/KCAOLYMP3_20260411_203035.png",
        "timestamp": "2026-04-11T20:30:35",
        "size": 133584,
        "type": "single"
      },
      "total_screenshots": 12,
      "all_screenshots": [
        {
          "filename": "KCAOLYMP3_20260411_203035.png",
          "path": "screenshots/KCAOLYMP3_20260411_203035.png",
          "timestamp": "2026-04-11T20:30:35",
          "size": 133584,
          "type": "single"
        },
        {
          "filename": "KCAOLYMP3_20260411_163439.png",
          "path": "screenshots/KCAOLYMP3_20260411_163439.png",
          "timestamp": "2026-04-11T16:34:39",
          "size": 130666,
          "type": "single"
        },
        {
          "filename": "KCAOLYMP3_20260411_125341.png",
          "path": "screenshots/KCAOLYMP3_20260411_125341.png",
          "timestamp": "2026-04-11T12:53:41",
          "size": 132727,
          "type": "single"
        },
        {
          "filename": "KCAOLYMP3_20260411_084034.png",
          "path": "screenshots/KCAOLYMP3_20260411_084034.png",
          "timestamp": "2026-04-11T08:40:34",
          "size": 131993,
          "type": "single"
        },
        {
          "filename": "KCAOLYMP3_20260411_052418.png",
          "path": "screenshots/KCAOLYMP3_20260411_052418.png",
          "timestamp": "2026-04-11T05:24:18",
          "size": 136404,
          "type": "single"
        },
        {
          "filename": "KCAOLYMP3_20260411_020354.png",
          "path": "screenshots/KCAOLYMP3_20260411_020354.png",
          "timestamp": "2026-04-11T02:03:54",
          "size": 131364,
          "type": "single"
        },
        {
          "filename": "KCAOLYMP3_20260410_203353.png",
          "path": "screenshots/KCAOLYMP3_20260410_203353.png",
          "timestamp": "2026-04-10T20:33:53",
          "size": 135147,
          "type": "single"
        },
        {
          "filename": "KCAOLYMP3_20260410_165206.png",
          "path": "screenshots/KCAOLYMP3_20260410_165206.png",
          "timestamp": "2026-04-10T16:52:06",
          "size": 136962,
          "type": "single"
        },
        {
          "filename": "KCAOLYMP3_20260410_130510.png",
          "path": "screenshots/KCAOLYMP3_20260410_130510.png",
          "timestamp": "2026-04-10T13:05:10",
          "size": 133651,
          "type": "single"
        },
        {
          "filename": "KCAOLYMP3_20260410_090631.png",
          "path": "screenshots/KCAOLYMP3_20260410_090631.png",
          "timestamp": "2026-04-10T09:06:31",
          "size": 135347,
          "type": "single"
        },
        {
          "filename": "KCAOLYMP3_20260410_055623.png",
          "path": "screenshots/KCAOLYMP3_20260410_055623.png",
          "timestamp": "2026-04-10T05:56:23",
          "size": 132612,
          "type": "single"
        },
        {
          "filename": "KCAOLYMP3_20260410_022313.png",
          "path": "screenshots/KCAOLYMP3_20260410_022313.png",
          "timestamp": "2026-04-10T02:23:13",
          "size": 133742,
          "type": "single"
        }
      ],
      "has_multiple_views": false,
      "is_full_page": false
    },
    "KNVRENO1473": {
      "latest_screenshot": {
        "filename": "KNVRENO1473_20260411_203023.png",
        "path": "screenshots/KNVRENO1473_20260411_203023.png",
        "timestamp": "2026-04-11T20:30:23",
        "size": 133581,
        "type": "single"
      },
      "total_screenshots": 12,
      "all_screenshots": [
        {
          "filename": "KNVRENO1473_20260411_203023.png",
          "path": "screenshots/KNVRENO1473_20260411_203023.png",
          "timestamp": "2026-04-11T20:30:23",
          "size": 133581,
          "type": "single"
        },
        {
          "filename": "KNVRENO1473_20260411_163427.png",
          "path": "screenshots/KNVRENO1473_20260411_163427.png",
          "timestamp": "2026-04-11T16:34:27",
          "size": 129480,
          "type": "single"
        },
        {
          "filename": "KNVRENO1473_20260411_125332.png",
          "path": "screenshots/KNVRENO1473_20260411_125332.png",
          "timestamp": "2026-04-11T12:53:32",
          "size": 127134,
          "type": "single"
        },
        {
          "filename": "KNVRENO1473_20260411_084026.png",
          "path": "screenshots/KNVRENO1473_20260411_084026.png",
          "timestamp": "2026-04-11T08:40:26",
          "size": 129180,
          "type": "single"
        },
        {
          "filename": "KNVRENO1473_20260411_052412.png",
          "path": "screenshots/KNVRENO1473_20260411_052412.png",
          "timestamp": "2026-04-11T05:24:12",
          "size": 130611,
          "type": "single"
        },
        {
          "filename": "KNVRENO1473_20260411_020342.png",
          "path": "screenshots/KNVRENO1473_20260411_020342.png",
          "timestamp": "2026-04-11T02:03:42",
          "size": 131778,
          "type": "single"
        },
        {
          "filename": "KNVRENO1473_20260410_203343.png",
          "path": "screenshots/KNVRENO1473_20260410_203343.png",
          "timestamp": "2026-04-10T20:33:43",
          "size": 135014,
          "type": "single"
        },
        {
          "filename": "KNVRENO1473_20260410_165158.png",
          "path": "screenshots/KNVRENO1473_20260410_165158.png",
          "timestamp": "2026-04-10T16:51:58",
          "size": 136296,
          "type": "single"
        },
        {
          "filename": "KNVRENO1473_20260410_130459.png",
          "path": "screenshots/KNVRENO1473_20260410_130459.png",
          "timestamp": "2026-04-10T13:04:59",
          "size": 132294,
          "type": "single"
        },
        {
          "filename": "KNVRENO1473_20260410_090618.png",
          "path": "screenshots/KNVRENO1473_20260410_090618.png",
          "timestamp": "2026-04-10T09:06:18",
          "size": 133561,
          "type": "single"
        },
        {
          "filename": "KNVRENO1473_20260410_055615.png",
          "path": "screenshots/KNVRENO1473_20260410_055615.png",
          "timestamp": "2026-04-10T05:56:15",
          "size": 137249,
          "type": "single"
        },
        {
          "filename": "KNVRENO1473_20260410_022305.png",
          "path": "screenshots/KNVRENO1473_20260410_022305.png",
          "timestamp": "2026-04-10T02:23:05",
          "size": 138138,
          "type": "single"
        }
      ],
      "has_multiple_views": false,
      "is_full_page": false
    },
    "NOAA_DESI_RENO": {
      "latest_screenshot": {
        "filename": "NOAA_DESI_RENO_20260411_203140.png",
        "path": "screenshots/NOAA_DESI_RENO_20260411_203140.png",
        "timestamp": "2026-04-11T20:31:40",
        "size": 415025,
        "type": "full_page"
      },
      "total_screenshots": 12,
      "all_screenshots": [
        {
          "filename": "NOAA_DESI_RENO_20260411_203140.png",
          "path": "screenshots/NOAA_DESI_RENO_20260411_203140.png",
          "timestamp": "2026-04-11T20:31:40",
          "size": 415025,
          "type": "full_page"
        },
        {
          "filename": "NOAA_DESI_RENO_20260411_163538.png",
          "path": "screenshots/NOAA_DESI_RENO_20260411_163538.png",
          "timestamp": "2026-04-11T16:35:38",
          "size": 416311,
          "type": "full_page"
        },
        {
          "filename": "NOAA_DESI_RENO_20260411_125441.png",
          "path": "screenshots/NOAA_DESI_RENO_20260411_125441.png",
          "timestamp": "2026-04-11T12:54:41",
          "size": 415326,
          "type": "full_page"
        },
        {
          "filename": "NOAA_DESI_RENO_20260411_084129.png",
          "path": "screenshots/NOAA_DESI_RENO_20260411_084129.png",
          "timestamp": "2026-04-11T08:41:29",
          "size": 413750,
          "type": "full_page"
        },
        {
          "filename": "NOAA_DESI_RENO_20260411_052512.png",
          "path": "screenshots/NOAA_DESI_RENO_20260411_052512.png",
          "timestamp": "2026-04-11T05:25:12",
          "size": 413750,
          "type": "full_page"
        },
        {
          "filename": "NOAA_DESI_RENO_20260411_020451.png",
          "path": "screenshots/NOAA_DESI_RENO_20260411_020451.png",
          "timestamp": "2026-04-11T02:04:51",
          "size": 414052,
          "type": "full_page"
        },
        {
          "filename": "NOAA_DESI_RENO_20260410_203452.png",
          "path": "screenshots/NOAA_DESI_RENO_20260410_203452.png",
          "timestamp": "2026-04-10T20:34:52",
          "size": 17564,
          "type": "full_page"
        },
        {
          "filename": "NOAA_DESI_RENO_20260410_165257.png",
          "path": "screenshots/NOAA_DESI_RENO_20260410_165257.png",
          "timestamp": "2026-04-10T16:52:57",
          "size": 17564,
          "type": "full_page"
        },
        {
          "filename": "NOAA_DESI_RENO_20260410_130621.png",
          "path": "screenshots/NOAA_DESI_RENO_20260410_130621.png",
          "timestamp": "2026-04-10T13:06:21",
          "size": 419434,
          "type": "full_page"
        },
        {
          "filename": "NOAA_DESI_RENO_20260410_090723.png",
          "path": "screenshots/NOAA_DESI_RENO_20260410_090723.png",
          "timestamp": "2026-04-10T09:07:23",
          "size": 352991,
          "type": "full_page"
        },
        {
          "filename": "NOAA_DESI_RENO_20260410_055718.png",
          "path": "screenshots/NOAA_DESI_RENO_20260410_055718.png",
          "timestamp": "2026-04-10T05:57:18",
          "size": 419569,
          "type": "full_page"
        },
        {
          "filename": "NOAA_DESI_RENO_20260410_022407.png",
          "path": "screenshots/NOAA_DESI_RENO_20260410_022407.png",
          "timestamp": "2026-04-10T02:24:07",
          "size": 419518,
          "type": "full_page"
        }
      ],
      "has_multiple_views": false,
      "is_full_page": true
    },
    "NOAA_DESI_HEAVENLY": {
      "latest_screenshot": {
        "filename": "NOAA_DESI_HEAVENLY_20260411_203157.png",
        "path": "screenshots/NOAA_DESI_HEAVENLY_20260411_203157.png",
        "timestamp": "2026-04-11T20:31:57",
        "size": 406204,
        "type": "full_page"
      },
      "total_screenshots": 12,
      "all_screenshots": [
        {
          "filename": "NOAA_DESI_HEAVENLY_20260411_203157.png",
          "path": "screenshots/NOAA_DESI_HEAVENLY_20260411_203157.png",
          "timestamp": "2026-04-11T20:31:57",
          "size": 406204,
          "type": "full_page"
        },
        {
          "filename": "NOAA_DESI_HEAVENLY_20260411_163556.png",
          "path": "screenshots/NOAA_DESI_HEAVENLY_20260411_163556.png",
          "timestamp": "2026-04-11T16:35:56",
          "size": 406392,
          "type": "full_page"
        },
        {
          "filename": "NOAA_DESI_HEAVENLY_20260411_125459.png",
          "path": "screenshots/NOAA_DESI_HEAVENLY_20260411_125459.png",
          "timestamp": "2026-04-11T12:54:59",
          "size": 407331,
          "type": "full_page"
        },
        {
          "filename": "NOAA_DESI_HEAVENLY_20260411_084148.png",
          "path": "screenshots/NOAA_DESI_HEAVENLY_20260411_084148.png",
          "timestamp": "2026-04-11T08:41:48",
          "size": 404894,
          "type": "full_page"
        },
        {
          "filename": "NOAA_DESI_HEAVENLY_20260411_052530.png",
          "path": "screenshots/NOAA_DESI_HEAVENLY_20260411_052530.png",
          "timestamp": "2026-04-11T05:25:30",
          "size": 404894,
          "type": "full_page"
        },
        {
          "filename": "NOAA_DESI_HEAVENLY_20260411_020509.png",
          "path": "screenshots/NOAA_DESI_HEAVENLY_20260411_020509.png",
          "timestamp": "2026-04-11T02:05:09",
          "size": 406704,
          "type": "full_page"
        },
        {
          "filename": "NOAA_DESI_HEAVENLY_20260410_203509.png",
          "path": "screenshots/NOAA_DESI_HEAVENLY_20260410_203509.png",
          "timestamp": "2026-04-10T20:35:09",
          "size": 17564,
          "type": "full_page"
        },
        {
          "filename": "NOAA_DESI_HEAVENLY_20260410_165313.png",
          "path": "screenshots/NOAA_DESI_HEAVENLY_20260410_165313.png",
          "timestamp": "2026-04-10T16:53:13",
          "size": 17564,
          "type": "full_page"
        },
        {
          "filename": "NOAA_DESI_HEAVENLY_20260410_130639.png",
          "path": "screenshots/NOAA_DESI_HEAVENLY_20260410_130639.png",
          "timestamp": "2026-04-10T13:06:39",
          "size": 177153,
          "type": "full_page"
        },
        {
          "filename": "NOAA_DESI_HEAVENLY_20260410_090741.png",
          "path": "screenshots/NOAA_DESI_HEAVENLY_20260410_090741.png",
          "timestamp": "2026-04-10T09:07:41",
          "size": 354652,
          "type": "full_page"
        },
        {
          "filename": "NOAA_DESI_HEAVENLY_20260410_055736.png",
          "path": "screenshots/NOAA_DESI_HEAVENLY_20260410_055736.png",
          "timestamp": "2026-04-10T05:57:36",
          "size": 411101,
          "type": "full_page"
        },
        {
          "filename": "NOAA_DESI_HEAVENLY_20260410_022425.png",
          "path": "screenshots/NOAA_DESI_HEAVENLY_20260410_022425.png",
          "timestamp": "2026-04-10T02:24:25",
          "size": 407567,
          "type": "full_page"
        }
      ],
      "has_multiple_views": false,
      "is_full_page": true
    }
  }
}