{
  "capture_time": "2026-05-31T13:41:55.156509",
  "screenshots": [
    {
      "location": "Alpine Meadows",
      "path": "screenshots/KCASQUAW15_20260531_134023.png",
      "timestamp": "2026-05-31T13:40:26.419277",
      "screenshot_type": "single"
    },
    {
      "location": "Downtown Reno",
      "path": "screenshots/KNVRENO1473_20260531_134030.png",
      "timestamp": "2026-05-31T13:40:34.495128",
      "screenshot_type": "single"
    },
    {
      "location": "Olympic Valley",
      "path": "screenshots/KCAOLYMP3_20260531_134038.png",
      "timestamp": "2026-05-31T13:40:42.399513",
      "screenshot_type": "single"
    },
    {
      "location": "Northstar at Tahoe",
      "path": "screenshots/KCATRUCK288_20260531_134046.png",
      "timestamp": "2026-05-31T13:40:50.227289",
      "screenshot_type": "single"
    },
    {
      "location": "Mt Rose (Sky Tavern)",
      "path": "screenshots/KNVRENO347_20260531_134056.png",
      "timestamp": "2026-05-31T13:40:59.976232",
      "screenshot_type": "single"
    },
    {
      "location": "NOAA DESI - Alpine Meadows Area",
      "path": "screenshots/NOAA_DESI_ALPINE_20260531_134117.png",
      "timestamp": "2026-05-31T13:41:18.075014",
      "screenshot_type": "full_page"
    },
    {
      "location": "NOAA DESI - Downtown Reno",
      "path": "screenshots/NOAA_DESI_RENO_20260531_134136.png",
      "timestamp": "2026-05-31T13:41:37.040146",
      "screenshot_type": "full_page"
    },
    {
      "location": "NOAA DESI - Heavenly Ski Resort",
      "path": "screenshots/NOAA_DESI_HEAVENLY_20260531_134154.png",
      "timestamp": "2026-05-31T13:41:55.056890",
      "screenshot_type": "full_page"
    }
  ]
}