{
  "capture_time": "2025-10-23T22:14:29.060502",
  "screenshots": [
    {
      "location": "Alpine Meadows",
      "path": "screenshots/KCASQUAW15_20251023_221331.png",
      "timestamp": "2025-10-23T22:13:34.074312",
      "screenshot_type": "single"
    },
    {
      "location": "Downtown Reno",
      "path": "screenshots/KNVRENO1473_20251023_221338.png",
      "timestamp": "2025-10-23T22:13:41.463041",
      "screenshot_type": "single"
    },
    {
      "location": "Olympic Valley (Squaw Valley)",
      "path": "screenshots/KCAOLYMP3_20251023_221345.png",
      "timestamp": "2025-10-23T22:13:48.526958",
      "screenshot_type": "single"
    },
    {
      "location": "Northstar at Tahoe (Truckee)",
      "path": "screenshots/KCATRUCK288_20251023_221352.png",
      "timestamp": "2025-10-23T22:13:54.820996",
      "screenshot_type": "single"
    },
    {
      "location": "Mt Rose (Sky Tavern)",
      "path": "screenshots/KNVRENO347_20251023_221359.png",
      "timestamp": "2025-10-23T22:14:01.293073",
      "screenshot_type": "single"
    },
    {
      "location": "NOAA DESI - Alpine Meadows Area",
      "path": "screenshots/NOAA_DESI_ALPINE_20251023_221410.png",
      "timestamp": "2025-10-23T22:14:10.444204",
      "screenshot_type": "full_page"
    },
    {
      "location": "NOAA DESI - Downtown Reno",
      "path": "screenshots/NOAA_DESI_RENO_20251023_221419.png",
      "timestamp": "2025-10-23T22:14:19.596103",
      "screenshot_type": "full_page"
    },
    {
      "location": "NOAA DESI - Heavenly Ski Resort",
      "path": "screenshots/NOAA_DESI_HEAVENLY_20251023_221428.png",
      "timestamp": "2025-10-23T22:14:28.979778",
      "screenshot_type": "full_page"
    }
  ]
}