{
  "capture_time": "2026-01-29T08:37:44.608403",
  "screenshots": [
    {
      "location": "Alpine Meadows",
      "path": "screenshots/KCASQUAW15_20260129_083613.png",
      "timestamp": "2026-01-29T08:36:17.503140",
      "screenshot_type": "single"
    },
    {
      "location": "Downtown Reno",
      "path": "screenshots/KNVRENO1473_20260129_083621.png",
      "timestamp": "2026-01-29T08:36:25.481583",
      "screenshot_type": "single"
    },
    {
      "location": "Olympic Valley",
      "path": "screenshots/KCAOLYMP3_20260129_083629.png",
      "timestamp": "2026-01-29T08:36:34.822855",
      "screenshot_type": "single"
    },
    {
      "location": "Northstar at Tahoe",
      "path": "screenshots/KCATRUCK288_20260129_083639.png",
      "timestamp": "2026-01-29T08:36:41.409159",
      "screenshot_type": "single"
    },
    {
      "location": "Mt Rose (Sky Tavern)",
      "path": "screenshots/KNVRENO347_20260129_083645.png",
      "timestamp": "2026-01-29T08:36:52.506779",
      "screenshot_type": "single"
    },
    {
      "location": "NOAA DESI - Alpine Meadows Area",
      "path": "screenshots/NOAA_DESI_ALPINE_20260129_083709.png",
      "timestamp": "2026-01-29T08:37:09.889537",
      "screenshot_type": "full_page"
    },
    {
      "location": "NOAA DESI - Downtown Reno",
      "path": "screenshots/NOAA_DESI_RENO_20260129_083727.png",
      "timestamp": "2026-01-29T08:37:27.204563",
      "screenshot_type": "full_page"
    },
    {
      "location": "NOAA DESI - Heavenly Ski Resort",
      "path": "screenshots/NOAA_DESI_HEAVENLY_20260129_083744.png",
      "timestamp": "2026-01-29T08:37:44.518565",
      "screenshot_type": "full_page"
    }
  ]
}