{
  "capture_time": "2025-11-13T08:25:54.094380",
  "screenshots": [
    {
      "location": "Alpine Meadows",
      "path": "screenshots/KCASQUAW15_20251113_082417.png",
      "timestamp": "2025-11-13T08:24:25.118738",
      "screenshot_type": "single"
    },
    {
      "location": "Downtown Reno",
      "path": "screenshots/KNVRENO1473_20251113_082429.png",
      "timestamp": "2025-11-13T08:24:37.713666",
      "screenshot_type": "single"
    },
    {
      "location": "Olympic Valley",
      "path": "screenshots/KCAOLYMP3_20251113_082442.png",
      "timestamp": "2025-11-13T08:24:48.603428",
      "screenshot_type": "single"
    },
    {
      "location": "Northstar at Tahoe",
      "path": "screenshots/KCATRUCK288_20251113_082453.png",
      "timestamp": "2025-11-13T08:24:56.473117",
      "screenshot_type": "single"
    },
    {
      "location": "Mt Rose (Sky Tavern)",
      "path": "screenshots/KNVRENO347_20251113_082500.png",
      "timestamp": "2025-11-13T08:25:01.211743",
      "screenshot_type": "single"
    },
    {
      "location": "NOAA DESI - Alpine Meadows Area",
      "path": "screenshots/NOAA_DESI_ALPINE_20251113_082518.png",
      "timestamp": "2025-11-13T08:25:18.875513",
      "screenshot_type": "full_page"
    },
    {
      "location": "NOAA DESI - Downtown Reno",
      "path": "screenshots/NOAA_DESI_RENO_20251113_082535.png",
      "timestamp": "2025-11-13T08:25:36.124497",
      "screenshot_type": "full_page"
    },
    {
      "location": "NOAA DESI - Heavenly Ski Resort",
      "path": "screenshots/NOAA_DESI_HEAVENLY_20251113_082553.png",
      "timestamp": "2025-11-13T08:25:54.009463",
      "screenshot_type": "full_page"
    }
  ]
}