{
  "capture_time": "2026-07-19T16:57:07.496548",
  "screenshots": [
    {
      "location": "Alpine Meadows",
      "path": "screenshots/KCASQUAW15_20260719_165535.png",
      "timestamp": "2026-07-19T16:55:37.797533",
      "screenshot_type": "single"
    },
    {
      "location": "Downtown Reno",
      "path": "screenshots/KNVRENO1473_20260719_165541.png",
      "timestamp": "2026-07-19T16:55:46.832427",
      "screenshot_type": "single"
    },
    {
      "location": "Olympic Valley",
      "path": "screenshots/KCAOLYMP3_20260719_165552.png",
      "timestamp": "2026-07-19T16:55:57.326214",
      "screenshot_type": "single"
    },
    {
      "location": "Northstar at Tahoe",
      "path": "screenshots/KCATRUCK288_20260719_165601.png",
      "timestamp": "2026-07-19T16:56:05.007838",
      "screenshot_type": "single"
    },
    {
      "location": "Mt Rose (Sky Tavern)",
      "path": "screenshots/KNVRENO347_20260719_165609.png",
      "timestamp": "2026-07-19T16:56:14.480635",
      "screenshot_type": "single"
    },
    {
      "location": "NOAA DESI - Alpine Meadows Area",
      "path": "screenshots/NOAA_DESI_ALPINE_20260719_165631.png",
      "timestamp": "2026-07-19T16:56:32.116819",
      "screenshot_type": "full_page"
    },
    {
      "location": "NOAA DESI - Downtown Reno",
      "path": "screenshots/NOAA_DESI_RENO_20260719_165649.png",
      "timestamp": "2026-07-19T16:56:49.669672",
      "screenshot_type": "full_page"
    },
    {
      "location": "NOAA DESI - Heavenly Ski Resort",
      "path": "screenshots/NOAA_DESI_HEAVENLY_20260719_165707.png",
      "timestamp": "2026-07-19T16:57:07.382514",
      "screenshot_type": "full_page"
    }
  ]
}