{
  "capture_time": "2025-12-24T20:21:34.234528",
  "screenshots": [
    {
      "location": "Alpine Meadows",
      "path": "screenshots/KCASQUAW15_20251224_201959.png",
      "timestamp": "2025-12-24T20:20:04.369207",
      "screenshot_type": "single"
    },
    {
      "location": "Downtown Reno",
      "path": "screenshots/KNVRENO1473_20251224_202008.png",
      "timestamp": "2025-12-24T20:20:14.078965",
      "screenshot_type": "single"
    },
    {
      "location": "Olympic Valley",
      "path": "screenshots/KCAOLYMP3_20251224_202018.png",
      "timestamp": "2025-12-24T20:20:24.833853",
      "screenshot_type": "single"
    },
    {
      "location": "Northstar at Tahoe",
      "path": "screenshots/KCATRUCK288_20251224_202029.png",
      "timestamp": "2025-12-24T20:20:32.402641",
      "screenshot_type": "single"
    },
    {
      "location": "Mt Rose (Sky Tavern)",
      "path": "screenshots/KNVRENO347_20251224_202036.png",
      "timestamp": "2025-12-24T20:20:42.018828",
      "screenshot_type": "single"
    },
    {
      "location": "NOAA DESI - Alpine Meadows Area",
      "path": "screenshots/NOAA_DESI_ALPINE_20251224_202059.png",
      "timestamp": "2025-12-24T20:20:59.430927",
      "screenshot_type": "full_page"
    },
    {
      "location": "NOAA DESI - Downtown Reno",
      "path": "screenshots/NOAA_DESI_RENO_20251224_202116.png",
      "timestamp": "2025-12-24T20:21:16.795620",
      "screenshot_type": "full_page"
    },
    {
      "location": "NOAA DESI - Heavenly Ski Resort",
      "path": "screenshots/NOAA_DESI_HEAVENLY_20251224_202133.png",
      "timestamp": "2025-12-24T20:21:34.138960",
      "screenshot_type": "full_page"
    }
  ]
}