{
  "capture_time": "2026-06-02T08:28:15.360029",
  "screenshots": [
    {
      "location": "Alpine Meadows",
      "path": "screenshots/KCASQUAW15_20260602_082645.png",
      "timestamp": "2026-06-02T08:26:46.305647",
      "screenshot_type": "single"
    },
    {
      "location": "Downtown Reno",
      "path": "screenshots/KNVRENO1473_20260602_082650.png",
      "timestamp": "2026-06-02T08:26:55.302431",
      "screenshot_type": "single"
    },
    {
      "location": "Olympic Valley",
      "path": "screenshots/KCAOLYMP3_20260602_082700.png",
      "timestamp": "2026-06-02T08:27:04.297792",
      "screenshot_type": "single"
    },
    {
      "location": "Northstar at Tahoe",
      "path": "screenshots/KCATRUCK288_20260602_082708.png",
      "timestamp": "2026-06-02T08:27:12.528135",
      "screenshot_type": "single"
    },
    {
      "location": "Mt Rose (Sky Tavern)",
      "path": "screenshots/KNVRENO347_20260602_082716.png",
      "timestamp": "2026-06-02T08:27:21.161888",
      "screenshot_type": "single"
    },
    {
      "location": "NOAA DESI - Alpine Meadows Area",
      "path": "screenshots/NOAA_DESI_ALPINE_20260602_082739.png",
      "timestamp": "2026-06-02T08:27:39.806459",
      "screenshot_type": "full_page"
    },
    {
      "location": "NOAA DESI - Downtown Reno",
      "path": "screenshots/NOAA_DESI_RENO_20260602_082757.png",
      "timestamp": "2026-06-02T08:27:57.773296",
      "screenshot_type": "full_page"
    },
    {
      "location": "NOAA DESI - Heavenly Ski Resort",
      "path": "screenshots/NOAA_DESI_HEAVENLY_20260602_082815.png",
      "timestamp": "2026-06-02T08:28:15.255558",
      "screenshot_type": "full_page"
    }
  ]
}