{
  "capture_time": "2026-05-23T06:33:15.677017",
  "screenshots": [
    {
      "location": "Alpine Meadows",
      "path": "screenshots/KCASQUAW15_20260523_063153.png",
      "timestamp": "2026-05-23T06:31:55.394204",
      "screenshot_type": "single"
    },
    {
      "location": "Downtown Reno",
      "path": "screenshots/KNVRENO1473_20260523_063159.png",
      "timestamp": "2026-05-23T06:32:02.207266",
      "screenshot_type": "single"
    },
    {
      "location": "Olympic Valley",
      "path": "screenshots/KCAOLYMP3_20260523_063206.png",
      "timestamp": "2026-05-23T06:32:08.270957",
      "screenshot_type": "single"
    },
    {
      "location": "Northstar at Tahoe",
      "path": "screenshots/KCATRUCK288_20260523_063212.png",
      "timestamp": "2026-05-23T06:32:14.717375",
      "screenshot_type": "single"
    },
    {
      "location": "Mt Rose (Sky Tavern)",
      "path": "screenshots/KNVRENO347_20260523_063218.png",
      "timestamp": "2026-05-23T06:32:22.909134",
      "screenshot_type": "single"
    },
    {
      "location": "NOAA DESI - Alpine Meadows Area",
      "path": "screenshots/NOAA_DESI_ALPINE_20260523_063240.png",
      "timestamp": "2026-05-23T06:32:40.443941",
      "screenshot_type": "full_page"
    },
    {
      "location": "NOAA DESI - Downtown Reno",
      "path": "screenshots/NOAA_DESI_RENO_20260523_063257.png",
      "timestamp": "2026-05-23T06:32:57.993363",
      "screenshot_type": "full_page"
    },
    {
      "location": "NOAA DESI - Heavenly Ski Resort",
      "path": "screenshots/NOAA_DESI_HEAVENLY_20260523_063315.png",
      "timestamp": "2026-05-23T06:33:15.590234",
      "screenshot_type": "full_page"
    }
  ]
}