{
  "capture_time": "2025-12-10T01:26:19.840723",
  "screenshots": [
    {
      "location": "Alpine Meadows",
      "path": "screenshots/KCASQUAW15_20251210_012451.png",
      "timestamp": "2025-12-10T01:24:51.572307",
      "screenshot_type": "single"
    },
    {
      "location": "Downtown Reno",
      "path": "screenshots/KNVRENO1473_20251210_012455.png",
      "timestamp": "2025-12-10T01:24:55.972718",
      "screenshot_type": "single"
    },
    {
      "location": "Olympic Valley",
      "path": "screenshots/KCAOLYMP3_20251210_012500.png",
      "timestamp": "2025-12-10T01:25:03.044426",
      "screenshot_type": "single"
    },
    {
      "location": "Northstar at Tahoe",
      "path": "screenshots/KCATRUCK288_20251210_012507.png",
      "timestamp": "2025-12-10T01:25:16.367216",
      "screenshot_type": "single"
    },
    {
      "location": "Mt Rose (Sky Tavern)",
      "path": "screenshots/KNVRENO347_20251210_012520.png",
      "timestamp": "2025-12-10T01:25:28.819397",
      "screenshot_type": "single"
    },
    {
      "location": "NOAA DESI - Alpine Meadows Area",
      "path": "screenshots/NOAA_DESI_ALPINE_20251210_012545.png",
      "timestamp": "2025-12-10T01:25:45.173927",
      "screenshot_type": "full_page"
    },
    {
      "location": "NOAA DESI - Downtown Reno",
      "path": "screenshots/NOAA_DESI_RENO_20251210_012602.png",
      "timestamp": "2025-12-10T01:26:02.454219",
      "screenshot_type": "full_page"
    },
    {
      "location": "NOAA DESI - Heavenly Ski Resort",
      "path": "screenshots/NOAA_DESI_HEAVENLY_20251210_012619.png",
      "timestamp": "2025-12-10T01:26:19.754118",
      "screenshot_type": "full_page"
    }
  ]
}