{
  "capture_time": "2026-06-07T21:11:23.118659",
  "screenshots": [
    {
      "location": "Alpine Meadows",
      "path": "screenshots/KCASQUAW15_20260607_210953.png",
      "timestamp": "2026-06-07T21:09:57.211676",
      "screenshot_type": "single"
    },
    {
      "location": "Downtown Reno",
      "path": "screenshots/KNVRENO1473_20260607_211001.png",
      "timestamp": "2026-06-07T21:10:05.318773",
      "screenshot_type": "single"
    },
    {
      "location": "Olympic Valley",
      "path": "screenshots/KCAOLYMP3_20260607_211010.png",
      "timestamp": "2026-06-07T21:10:14.171522",
      "screenshot_type": "single"
    },
    {
      "location": "Northstar at Tahoe",
      "path": "screenshots/KCATRUCK288_20260607_211018.png",
      "timestamp": "2026-06-07T21:10:22.371866",
      "screenshot_type": "single"
    },
    {
      "location": "Mt Rose (Sky Tavern)",
      "path": "screenshots/KNVRENO347_20260607_211026.png",
      "timestamp": "2026-06-07T21:10:30.324985",
      "screenshot_type": "single"
    },
    {
      "location": "NOAA DESI - Alpine Meadows Area",
      "path": "screenshots/NOAA_DESI_ALPINE_20260607_211047.png",
      "timestamp": "2026-06-07T21:10:47.909097",
      "screenshot_type": "full_page"
    },
    {
      "location": "NOAA DESI - Downtown Reno",
      "path": "screenshots/NOAA_DESI_RENO_20260607_211105.png",
      "timestamp": "2026-06-07T21:11:05.403887",
      "screenshot_type": "full_page"
    },
    {
      "location": "NOAA DESI - Heavenly Ski Resort",
      "path": "screenshots/NOAA_DESI_HEAVENLY_20260607_211122.png",
      "timestamp": "2026-06-07T21:11:22.951721",
      "screenshot_type": "full_page"
    }
  ]
}