{
  "capture_time": "2026-06-11T08:45:20.765360",
  "screenshots": [
    {
      "location": "Alpine Meadows",
      "path": "screenshots/KCASQUAW15_20260611_084354.png",
      "timestamp": "2026-06-11T08:43:56.882263",
      "screenshot_type": "single"
    },
    {
      "location": "Downtown Reno",
      "path": "screenshots/KNVRENO1473_20260611_084401.png",
      "timestamp": "2026-06-11T08:44:02.517192",
      "screenshot_type": "single"
    },
    {
      "location": "Olympic Valley",
      "path": "screenshots/KCAOLYMP3_20260611_084407.png",
      "timestamp": "2026-06-11T08:44:10.098463",
      "screenshot_type": "single"
    },
    {
      "location": "Northstar at Tahoe",
      "path": "screenshots/KCATRUCK288_20260611_084415.png",
      "timestamp": "2026-06-11T08:44:17.164487",
      "screenshot_type": "single"
    },
    {
      "location": "Mt Rose (Sky Tavern)",
      "path": "screenshots/KNVRENO347_20260611_084422.png",
      "timestamp": "2026-06-11T08:44:24.891382",
      "screenshot_type": "single"
    },
    {
      "location": "NOAA DESI - Alpine Meadows Area",
      "path": "screenshots/NOAA_DESI_ALPINE_20260611_084443.png",
      "timestamp": "2026-06-11T08:44:43.629546",
      "screenshot_type": "full_page"
    },
    {
      "location": "NOAA DESI - Downtown Reno",
      "path": "screenshots/NOAA_DESI_RENO_20260611_084502.png",
      "timestamp": "2026-06-11T08:45:02.181823",
      "screenshot_type": "full_page"
    },
    {
      "location": "NOAA DESI - Heavenly Ski Resort",
      "path": "screenshots/NOAA_DESI_HEAVENLY_20260611_084520.png",
      "timestamp": "2026-06-11T08:45:20.676886",
      "screenshot_type": "full_page"
    }
  ]
}