{
  "capture_time": "2026-01-09T08:29:21.786411",
  "screenshots": [
    {
      "location": "Alpine Meadows",
      "path": "screenshots/KCASQUAW15_20260109_082758.png",
      "timestamp": "2026-01-09T08:27:59.034357",
      "screenshot_type": "single"
    },
    {
      "location": "Downtown Reno",
      "path": "screenshots/KNVRENO1473_20260109_082804.png",
      "timestamp": "2026-01-09T08:28:09.257807",
      "screenshot_type": "single"
    },
    {
      "location": "Olympic Valley",
      "path": "screenshots/KCAOLYMP3_20260109_082813.png",
      "timestamp": "2026-01-09T08:28:16.535713",
      "screenshot_type": "single"
    },
    {
      "location": "Northstar at Tahoe",
      "path": "screenshots/KCATRUCK288_20260109_082820.png",
      "timestamp": "2026-01-09T08:28:22.514882",
      "screenshot_type": "single"
    },
    {
      "location": "Mt Rose (Sky Tavern)",
      "path": "screenshots/KNVRENO347_20260109_082826.png",
      "timestamp": "2026-01-09T08:28:28.851422",
      "screenshot_type": "single"
    },
    {
      "location": "NOAA DESI - Alpine Meadows Area",
      "path": "screenshots/NOAA_DESI_ALPINE_20260109_082846.png",
      "timestamp": "2026-01-09T08:28:46.558653",
      "screenshot_type": "full_page"
    },
    {
      "location": "NOAA DESI - Downtown Reno",
      "path": "screenshots/NOAA_DESI_RENO_20260109_082903.png",
      "timestamp": "2026-01-09T08:29:04.095210",
      "screenshot_type": "full_page"
    },
    {
      "location": "NOAA DESI - Heavenly Ski Resort",
      "path": "screenshots/NOAA_DESI_HEAVENLY_20260109_082921.png",
      "timestamp": "2026-01-09T08:29:21.688646",
      "screenshot_type": "full_page"
    }
  ]
}