{
  "capture_time": "2026-05-11T11:00:06.578697",
  "screenshots": [
    {
      "location": "Alpine Meadows",
      "path": "screenshots/KCASQUAW15_20260511_105846.png",
      "timestamp": "2026-05-11T10:58:47.738200",
      "screenshot_type": "single"
    },
    {
      "location": "Downtown Reno",
      "path": "screenshots/KNVRENO1473_20260511_105853.png",
      "timestamp": "2026-05-11T10:58:55.322956",
      "screenshot_type": "single"
    },
    {
      "location": "Olympic Valley",
      "path": "screenshots/KCAOLYMP3_20260511_105859.png",
      "timestamp": "2026-05-11T10:59:01.489841",
      "screenshot_type": "single"
    },
    {
      "location": "Northstar at Tahoe",
      "path": "screenshots/KCATRUCK288_20260511_105905.png",
      "timestamp": "2026-05-11T10:59:06.958116",
      "screenshot_type": "single"
    },
    {
      "location": "Mt Rose (Sky Tavern)",
      "path": "screenshots/KNVRENO347_20260511_105911.png",
      "timestamp": "2026-05-11T10:59:12.981604",
      "screenshot_type": "single"
    },
    {
      "location": "NOAA DESI - Alpine Meadows Area",
      "path": "screenshots/NOAA_DESI_ALPINE_20260511_105930.png",
      "timestamp": "2026-05-11T10:59:31.023702",
      "screenshot_type": "full_page"
    },
    {
      "location": "NOAA DESI - Downtown Reno",
      "path": "screenshots/NOAA_DESI_RENO_20260511_105948.png",
      "timestamp": "2026-05-11T10:59:48.504681",
      "screenshot_type": "full_page"
    },
    {
      "location": "NOAA DESI - Heavenly Ski Resort",
      "path": "screenshots/NOAA_DESI_HEAVENLY_20260511_110006.png",
      "timestamp": "2026-05-11T11:00:06.486041",
      "screenshot_type": "full_page"
    }
  ]
}