{
  "capture_time": "2026-07-10T02:47:51.693310",
  "screenshots": [
    {
      "location": "Alpine Meadows",
      "path": "screenshots/KCASQUAW15_20260710_024627.png",
      "timestamp": "2026-07-10T02:46:31.126959",
      "screenshot_type": "single"
    },
    {
      "location": "Downtown Reno",
      "path": "screenshots/KNVRENO1473_20260710_024635.png",
      "timestamp": "2026-07-10T02:46:39.325577",
      "screenshot_type": "single"
    },
    {
      "location": "Olympic Valley",
      "path": "screenshots/KCAOLYMP3_20260710_024643.png",
      "timestamp": "2026-07-10T02:46:47.826342",
      "screenshot_type": "single"
    },
    {
      "location": "Northstar at Tahoe",
      "path": "screenshots/KCATRUCK288_20260710_024652.png",
      "timestamp": "2026-07-10T02:46:52.628977",
      "screenshot_type": "single"
    },
    {
      "location": "Mt Rose (Sky Tavern)",
      "path": "screenshots/KNVRENO347_20260710_024657.png",
      "timestamp": "2026-07-10T02:46:59.080907",
      "screenshot_type": "single"
    },
    {
      "location": "NOAA DESI - Alpine Meadows Area",
      "path": "screenshots/NOAA_DESI_ALPINE_20260710_024716.png",
      "timestamp": "2026-07-10T02:47:16.651063",
      "screenshot_type": "full_page"
    },
    {
      "location": "NOAA DESI - Downtown Reno",
      "path": "screenshots/NOAA_DESI_RENO_20260710_024733.png",
      "timestamp": "2026-07-10T02:47:34.155012",
      "screenshot_type": "full_page"
    },
    {
      "location": "NOAA DESI - Heavenly Ski Resort",
      "path": "screenshots/NOAA_DESI_HEAVENLY_20260710_024751.png",
      "timestamp": "2026-07-10T02:47:51.614393",
      "screenshot_type": "full_page"
    }
  ]
}